leaping.py
leaping-0.1.14.dist-info/METADATA
leaping-0.1.14.dist-info/WHEEL
leaping-0.1.14.dist-info/entry_points.txt
leaping-0.1.14.dist-info/top_level.txt
leaping-0.1.14.dist-info/RECORD
